arff_converter/__init__.py
arff_converter/converter.py
arff_converter-0.2.0.dist-info/LICENSE
arff_converter-0.2.0.dist-info/METADATA
arff_converter-0.2.0.dist-info/WHEEL
arff_converter-0.2.0.dist-info/entry_points.txt
arff_converter-0.2.0.dist-info/top_level.txt
arff_converter-0.2.0.dist-info/RECORD
