Metadata-Version: 2.1
Name: arff-converter
Version: 0.2.0
Summary: A simple converter from ARFF to XLSX format
Home-page: https://github.com/Brad-Edwards/arff-converter
Author: Brad Edwards
Author-email: atomik@atomiklabs.com
Classifier: Programming Language :: Python :: 3
Classifier: License :: OSI Approved :: MIT License
Classifier: Operating System :: OS Independent
Requires-Python: >=3.6
License-File: LICENSE
Requires-Dist: pandas
Requires-Dist: openpyxl
